jobboard/__init__.py
jobboard/admin.py
jobboard/apps.py
jobboard/models.py
jobboard/tests.py
jobboard/urls.py
jobboard/views.py
jobboard/migrations/0001_initial.py
jobboard/migrations/0002_auto_20190715_1813.py
jobboard/migrations/__init__.py
jobboard/templates/jobboard/base.html
jobboard/templates/jobboard/jobposting_detail.html
jobboard/templates/jobboard/jobposting_list.html
django_jobboard-0.1.0.dist-info/LICENSE
django_jobboard-0.1.0.dist-info/METADATA
django_jobboard-0.1.0.dist-info/WHEEL
django_jobboard-0.1.0.dist-info/top_level.txt
django_jobboard-0.1.0.dist-info/RECORD
